{
    "@class": "com.kony.gen.viz.model.container.KVizSegment2",
    "DNDConfig": null,
    "__parentReadjusting__": false,
    "_data_": [
        {
            "imgRekomendasi": {
                "@class": "com.viz.ide.model.segment.ImageSegmentData",
                "src": "imagedrag.png"
            },
            "lblDistance": {
                "@class": "com.viz.ide.model.segment.SimpleTextSegmentData",
                "text": "Label"
            },
            "lblNama": {
                "@class": "com.viz.ide.model.segment.SimpleTextSegmentData",
                "text": "Label"
            },
            "lblPrice": {
                "@class": "com.viz.ide.model.segment.SimpleTextSegmentData",
                "text": "Label"
            },
            "lblRating": {
                "@class": "com.viz.ide.model.segment.SimpleTextSegmentData",
                "text": "Label"
            }
        },
        {
            "imgRekomendasi": {
                "@class": "com.viz.ide.model.segment.ImageSegmentData",
                "src": "imagedrag.png"
            },
            "lblDistance": {
                "@class": "com.viz.ide.model.segment.SimpleTextSegmentData",
                "text": "Label"
            },
            "lblNama": {
                "@class": "com.viz.ide.model.segment.SimpleTextSegmentData",
                "text": "Label"
            },
            "lblPrice": {
                "@class": "com.viz.ide.model.segment.SimpleTextSegmentData",
                "text": "Label"
            },
            "lblRating": {
                "@class": "com.viz.ide.model.segment.SimpleTextSegmentData",
                "text": "Label"
            }
        },
        {
            "imgRekomendasi": {
                "@class": "com.viz.ide.model.segment.ImageSegmentData",
                "src": "imagedrag.png"
            },
            "lblDistance": {
                "@class": "com.viz.ide.model.segment.SimpleTextSegmentData",
                "text": "Label"
            },
            "lblNama": {
                "@class": "com.viz.ide.model.segment.SimpleTextSegmentData",
                "text": "Label"
            },
            "lblPrice": {
                "@class": "com.viz.ide.model.segment.SimpleTextSegmentData",
                "text": "Label"
            },
            "lblRating": {
                "@class": "com.viz.ide.model.segment.SimpleTextSegmentData",
                "text": "Label"
            }
        }
    ],
    "_height_": {
        "type": "ref",
        "value": "preferred"
    },
    "_indicator_": "none",
    "_left_": {
        "type": "string",
        "value": "25dp"
    },
    "_margin_": [
        0,
        0,
        0,
        0
    ],
    "_orientation_": 2,
    "_padding_": [
        0,
        0,
        0,
        0
    ],
    "_top_": {
        "type": "string",
        "value": "10dp"
    },
    "_width_": {
        "type": "string",
        "value": "86.09%"
    },
    "autogrowmode": 1,
    "canUpdateUI": true,
    "containerweight": 100,
    "counter": "02",
    "enablereordering": false,
    "focusedindex": null,
    "focuseditem": null,
    "generatedtemplate": "e2402127ebce43cc8b7ade7b525a2afa",
    "groupcells": false,
    "hasSections": false,
    "id": "sgmRekomendasi",
    "info": null,
    "ipad": {
        "psp": {
            "indicator": "rowselect"
        }
    },
    "iphone": {
        "psp": {
            "indicator": "rowselect"
        }
    },
    "isvisible": true,
    "kuid": "d48dab80867d4f069658649c8b81bd70",
    "masterdata": {},
    "name": "kony.ui.SegmentedUI2",
    "needpageindicator": true,
    "pageoffdotimage": "pageoffdot.png",
    "pageondotimage": "pageondot.png",
    "paginationconfig": {
        "position": "bottom"
    },
    "parent": "flxContentTourist",
    "pf": "frmTourist",
    "retainselection": false,
    "rowTemplateId": "e2402127ebce43cc8b7ade7b525a2afa",
    "rowcounter": 2,
    "rowfocusskin": "s19ee5ddc5fc47af85405692cffd2911",
    "rowskin": "s6f3539c342947659190892d43ad46f2",
    "rowtemplate": "FBox0fb423bc6f8354f",
    "screenlevelwidget": false,
    "seccounter": 0,
    "sectionheaderskin": "s1c7fbd7dfbd4692979ffb1d63c41e54",
    "selectedRows": null,
    "selectedState": false,
    "selectedindex": null,
    "selectedindices": null,
    "selecteditems": null,
    "selectedsectionindex": 0,
    "selectionbehavior": "default",
    "separatorcolor": "64646400",
    "separatorrequired": true,
    "separatorthickness": 1,
    "showscrollbars": false,
    "viewtype": "tableview",
    "wType": "Segment",
    "widgetalignment": 5,
    "widgetdatamap": {
        "imgRekomendasi": "imgRekomendasi",
        "lblDistance": "lblDistance",
        "lblNama": "lblNama",
        "lblPrice": "lblPrice",
        "lblRating": "lblRating"
    },
    "zindex": 1
}